mtbacktest/__init__.py
mtbacktest/backtest.py
mtbacktest/data.py
mtbacktest/examples.py
mtbacktest/simulation.py
mtbacktest/strategy.py
mtbacktest/lib/__init__.py
mtbacktest/lib/metrics.py
mtbacktest/lib/preprocessing.py
mtbacktest/lib/utils.py
mtbacktest-0.1.18.dist-info/LICENSE
mtbacktest-0.1.18.dist-info/METADATA
mtbacktest-0.1.18.dist-info/WHEEL
mtbacktest-0.1.18.dist-info/top_level.txt
mtbacktest-0.1.18.dist-info/RECORD
