Metadata-Version: 2.2
Name: mtbacktest
Version: 0.1.18
Summary: A packaged designed for backtesting single and multi ticker strategies
Author-email: Jiajian He <2211054370abc@gmail.com>
Project-URL: Homepage, https://github.com/jeffhe1/mtbacktest
Classifier: Programming Language :: Python :: 3
Classifier: License :: OSI Approved :: MIT License
Classifier: Operating System :: OS Independent
Requires-Python: >=3.8
License-File: LICENSE
